eptr2/__init__.py
eptr2/main.py
eptr2/composite/__init__.py
eptr2/composite/bpm.py
eptr2/composite/consumption.py
eptr2/composite/dabi_idm.py
eptr2/composite/idm_log.py
eptr2/composite/ids.py
eptr2/composite/mms.py
eptr2/composite/periodic_orgs.py
eptr2/composite/plant_costs.py
eptr2/composite/price_and_cost.py
eptr2/composite/production.py
eptr2/mapping/__init__.py
eptr2/mapping/checks.py
eptr2/mapping/help.py
eptr2/mapping/parameters.py
eptr2/mapping/path.py
eptr2/mapping/processing.py
eptr2/mcp/README.md
eptr2/mcp/__init__.py
eptr2/mcp/server.py
eptr2/processing/__init__.py
eptr2/processing/postprocess/__init__.py
eptr2/processing/postprocess/items.py
eptr2/processing/preprocess/__init__.py
eptr2/processing/preprocess/calls.py
eptr2/processing/preprocess/params.py
eptr2/util/__init__.py
eptr2/util/certificate.py
eptr2/util/costs.py
eptr2/util/evaluation.py
eptr2/util/time.py
eptr2-1.3.4.dist-info/METADATA
eptr2-1.3.4.dist-info/WHEEL
eptr2-1.3.4.dist-info/entry_points.txt
eptr2-1.3.4.dist-info/licenses/LICENSE
eptr2-1.3.4.dist-info/RECORD
