Metadata-Version: 2.4
Name: eptr2
Version: 1.3.4
Summary: EPIAS Transparency Platform v2.0 Python client by Robokami / Tideseed
Author-email: Tideseed <info@tideseed.com>
License: Apache License 2.0
License-File: LICENSE
Requires-Python: >=3.10
Requires-Dist: pytz>=2024.1
Requires-Dist: urllib3>=2.6.3
Provides-Extra: allextras
Requires-Dist: fastmcp>=0.2.0; extra == 'allextras'
Requires-Dist: openpyxl>=3.1.5; extra == 'allextras'
Requires-Dist: pandas>=2.1.3; extra == 'allextras'
Requires-Dist: requests>=2.32.4; extra == 'allextras'
Requires-Dist: streamlit>=1.50.0; extra == 'allextras'
Requires-Dist: tornado>=6.5.0; extra == 'allextras'
Requires-Dist: xlsxwriter>=3.2.9; extra == 'allextras'
Provides-Extra: dataframe
Requires-Dist: pandas>=2.1.3; extra == 'dataframe'
Provides-Extra: dev
Requires-Dist: pytest>=7.4.0; extra == 'dev'
Provides-Extra: docs
Requires-Dist: mkdocs-autorefs>=0.5.0; extra == 'docs'
Requires-Dist: mkdocs-material>=9.5.0; extra == 'docs'
Requires-Dist: mkdocstrings[python]>=0.24.0; extra == 'docs'
Provides-Extra: mcp
Requires-Dist: fastmcp>=0.2.0; extra == 'mcp'
Requires-Dist: pandas>=2.1.3; extra == 'mcp'
